ewoksorange/__init__.py
ewoksorange/discovery.py
ewoksorange/engine.py
ewoksorange/orange_version.py
ewoksorange/pkg_meta.py
ewoksorange/registration.py
ewoksorange/bindings/__init__.py
ewoksorange/bindings/bindings.py
ewoksorange/bindings/events.py
ewoksorange/bindings/invalid_data.py
ewoksorange/bindings/owsconvert.py
ewoksorange/bindings/owsettings.py
ewoksorange/bindings/owsignal_manager.py
ewoksorange/bindings/owwidgets.py
ewoksorange/bindings/progress.py
ewoksorange/bindings/qtapp.py
ewoksorange/bindings/taskexecuter.py
ewoksorange/bindings/taskexecutor_queue.py
ewoksorange/bindings/taskwrapper.py
ewoksorange/canvas/__init__.py
ewoksorange/canvas/__main__.py
ewoksorange/canvas/config.py
ewoksorange/canvas/handler.py
ewoksorange/canvas/main.py
ewoksorange/canvas/utils.py
ewoksorange/gui/__init__.py
ewoksorange/gui/_oasys_patch.py
ewoksorange/gui/_patch_on_import.py
ewoksorange/gui/data_viewer.py
ewoksorange/gui/orange_imports.py
ewoksorange/gui/parameterform.py
ewoksorange/gui/qtsignals.py
ewoksorange/gui/simpletypesmixin.py
ewoksorange/gui/canvas/__init__.py
ewoksorange/gui/canvas/__main__.py
ewoksorange/gui/canvas/config.py
ewoksorange/gui/canvas/handler.py
ewoksorange/gui/canvas/main.py
ewoksorange/gui/canvas/utils.py
ewoksorange/gui/concurrency/__init__.py
ewoksorange/gui/concurrency/base.py
ewoksorange/gui/concurrency/queued.py
ewoksorange/gui/concurrency/threaded.py
ewoksorange/gui/orange_utils/__init__.py
ewoksorange/gui/orange_utils/_signals.py
ewoksorange/gui/orange_utils/orange_imports.py
ewoksorange/gui/orange_utils/settings.py
ewoksorange/gui/orange_utils/signal_manager.py
ewoksorange/gui/orange_utils/signals.py
ewoksorange/gui/owwidgets/__init__.py
ewoksorange/gui/owwidgets/base.py
ewoksorange/gui/owwidgets/meta.py
ewoksorange/gui/owwidgets/nothread.py
ewoksorange/gui/owwidgets/registration.py
ewoksorange/gui/owwidgets/summarizers.py
ewoksorange/gui/owwidgets/threaded.py
ewoksorange/gui/owwidgets/types.py
ewoksorange/gui/qt_utils/__init__.py
ewoksorange-3.3.1.dist-info/licenses/LICENSE.md
ewoksorange-3.3.1.dist-info/METADATA
ewoksorange-3.3.1.dist-info/WHEEL
ewoksorange-3.3.1.dist-info/entry_points.txt
ewoksorange-3.3.1.dist-info/top_level.txt
ewoksorange-3.3.1.dist-info/RECORD
