Metadata-Version: 2.4
Name: ewoksorange
Version: 3.3.1
Summary: Orange binding for Ewoks
Author-email: ESRF <dau-pydev@esrf.fr>
License: # MIT License
Project-URL: Homepage, https://gitlab.esrf.fr/workflow/ewoks/ewoksorange/
Project-URL: Documentation, https://ewoksorange.readthedocs.io/
Project-URL: Repository, https://gitlab.esrf.fr/workflow/ewoks/ewoksorange/
Project-URL: Issues, https://gitlab.esrf.fr/workflow/ewoks/ewoksorange/issues
Project-URL: Changelog, https://gitlab.esrf.fr/workflow/ewoks/ewoksorange/-/blob/main/CHANGELOG.md
Classifier: Intended Audience :: Science/Research
Classifier: License :: OSI Approved :: MIT License
Classifier: Programming Language :: Python :: 3
Requires-Python: >=3.8
License-File: LICENSE.md
Requires-Dist: ewokscore>=4.0.1
Requires-Dist: orange-canvas-core
Requires-Dist: orange-widget-base>=4.13.0
Requires-Dist: importlib-resources; python_version < "3.9"
Requires-Dist: importlib-metadata; python_version < "3.9"
Requires-Dist: packaging
Provides-Extra: full
Requires-Dist: PyQt6; extra == "full"
Provides-Extra: test
Requires-Dist: ewoksorange[full]; extra == "test"
Requires-Dist: pytest>=7; extra == "test"
Requires-Dist: pytest-timeout; extra == "test"
Provides-Extra: dev
Requires-Dist: ewoksorange[test]; extra == "dev"
Requires-Dist: black>=25; extra == "dev"
Requires-Dist: flake8>=4; extra == "dev"
Provides-Extra: doc
Requires-Dist: ewoksorange[test]; extra == "doc"
Requires-Dist: sphinx>=4.5; extra == "doc"
Requires-Dist: sphinx-autodoc-typehints>=1.16; extra == "doc"
Requires-Dist: sphinx-design; extra == "doc"
Requires-Dist: sphinx-togglebutton; extra == "doc"
Requires-Dist: pydata-sphinx-theme; extra == "doc"
Requires-Dist: sphinx-copybutton; extra == "doc"
Requires-Dist: sphinxcontrib-mermaid; extra == "doc"
Provides-Extra: orange
Requires-Dist: bottleneck<1.4.1; python_version < "3.9" and extra == "orange"
Requires-Dist: Orange3; extra == "orange"
Dynamic: license-file
